{
  "wallpaper": "/home/diaz/Pictures/Wallpapers/dvp4qg18e9jg1.jpeg",
  "mode": "light",
  "variant": "fidelity",
  "source_color": "#2a82b5",
  "colors": {
    "m3primary": "#00628e",
    "m3onPrimary": "#ffffff",
    "m3primaryContainer": "#1f7bae",
    "m3onPrimaryContainer": "#fcfcff",
    "m3primaryFixed": "#c9e6ff",
    "m3primaryFixedDim": "#8bceff",
    "m3onPrimaryFixed": "#001e2f",
    "m3onPrimaryFixedVariant": "#004b6f",
    "m3secondary": "#476176",
    "m3onSecondary": "#ffffff",
    "m3secondaryContainer": "#cae6ff",
    "m3onSecondaryContainer": "#4d677c",
    "m3secondaryFixed": "#cae6ff",
    "m3secondaryFixedDim": "#aecae2",
    "m3onSecondaryFixed": "#001e2f",
    "m3onSecondaryFixedVariant": "#2f4a5d",
    "m3tertiary": "#864f00",
    "m3onTertiary": "#ffffff",
    "m3tertiaryContainer": "#a66613",
    "m3onTertiaryContainer": "#fffbff",
    "m3tertiaryFixed": "#ffdcbd",
    "m3tertiaryFixedDim": "#ffb86e",
    "m3onTertiaryFixed": "#2c1600",
    "m3onTertiaryFixedVariant": "#693c00",
    "m3error": "#ba1a1a",
    "m3onError": "#ffffff",
    "m3errorContainer": "#ffdad6",
    "m3onErrorContainer": "#93000a",
    "m3surface": "#f7f9fe",
    "m3onSurface": "#181c1f",
    "m3surfaceVariant": "#dbe3ec",
    "m3onSurfaceVariant": "#40484f",
    "m3surfaceDim": "#d8dadf",
    "m3surfaceBright": "#f7f9fe",
    "m3surfaceContainerLowest": "#ffffff",
    "m3surfaceContainerLow": "#f1f4f8",
    "m3surfaceContainer": "#eceef2",
    "m3surfaceContainerHigh": "#e6e8ed",
    "m3surfaceContainerHighest": "#e0e3e7",
    "m3background": "#f7f9fe",
    "m3onBackground": "#181c1f",
    "m3outline": "#707880",
    "m3outlineVariant": "#bfc7d0",
    "m3inverseSurface": "#2d3134",
    "m3inverseOnSurface": "#eef1f5",
    "m3inversePrimary": "#8bceff",
    "m3shadow": "#000000",
    "m3scrim": "#000000",
    "term0": "#e0e3e7",
    "term1": "#ba1a1a",
    "term2": "#693c00",
    "term3": "#2f4a5d",
    "term4": "#00628e",
    "term5": "#476176",
    "term6": "#707880",
    "term7": "#40484f",
    "term8": "#864f00",
    "term9": "#93000a",
    "term10": "#ffb86e",
    "term11": "#004b6f",
    "term12": "#fcfcff",
    "term13": "#4d677c",
    "term14": "#8bceff",
    "term15": "#d8dadf",
    "m3primary_rgb": "0,98,142",
    "m3onPrimary_rgb": "255,255,255",
    "m3primaryContainer_rgb": "31,123,174",
    "m3onPrimaryContainer_rgb": "252,252,255",
    "m3primaryFixed_rgb": "201,230,255",
    "m3primaryFixedDim_rgb": "139,206,255",
    "m3onPrimaryFixed_rgb": "0,30,47",
    "m3onPrimaryFixedVariant_rgb": "0,75,111",
    "m3secondary_rgb": "71,97,118",
    "m3onSecondary_rgb": "255,255,255",
    "m3secondaryContainer_rgb": "202,230,255",
    "m3onSecondaryContainer_rgb": "77,103,124",
    "m3secondaryFixed_rgb": "202,230,255",
    "m3secondaryFixedDim_rgb": "174,202,226",
    "m3onSecondaryFixed_rgb": "0,30,47",
    "m3onSecondaryFixedVariant_rgb": "47,74,93",
    "m3tertiary_rgb": "134,79,0",
    "m3onTertiary_rgb": "255,255,255",
    "m3tertiaryContainer_rgb": "166,102,19",
    "m3onTertiaryContainer_rgb": "255,251,255",
    "m3tertiaryFixed_rgb": "255,220,189",
    "m3tertiaryFixedDim_rgb": "255,184,110",
    "m3onTertiaryFixed_rgb": "44,22,0",
    "m3onTertiaryFixedVariant_rgb": "105,60,0",
    "m3error_rgb": "186,26,26",
    "m3onError_rgb": "255,255,255",
    "m3errorContainer_rgb": "255,218,214",
    "m3onErrorContainer_rgb": "147,0,10",
    "m3surface_rgb": "247,249,254",
    "m3onSurface_rgb": "24,28,31",
    "m3surfaceVariant_rgb": "219,227,236",
    "m3onSurfaceVariant_rgb": "64,72,79",
    "m3surfaceDim_rgb": "216,218,223",
    "m3surfaceBright_rgb": "247,249,254",
    "m3surfaceContainerLowest_rgb": "255,255,255",
    "m3surfaceContainerLow_rgb": "241,244,248",
    "m3surfaceContainer_rgb": "236,238,242",
    "m3surfaceContainerHigh_rgb": "230,232,237",
    "m3surfaceContainerHighest_rgb": "224,227,231",
    "m3background_rgb": "247,249,254",
    "m3onBackground_rgb": "24,28,31",
    "m3outline_rgb": "112,120,128",
    "m3outlineVariant_rgb": "191,199,208",
    "m3inverseSurface_rgb": "45,49,52",
    "m3inverseOnSurface_rgb": "238,241,245",
    "m3inversePrimary_rgb": "139,206,255",
    "m3shadow_rgb": "0,0,0",
    "m3scrim_rgb": "0,0,0",
    "term0_rgb": "224,227,231",
    "term1_rgb": "186,26,26",
    "term2_rgb": "105,60,0",
    "term3_rgb": "47,74,93",
    "term4_rgb": "0,98,142",
    "term5_rgb": "71,97,118",
    "term6_rgb": "112,120,128",
    "term7_rgb": "64,72,79",
    "term8_rgb": "134,79,0",
    "term9_rgb": "147,0,10",
    "term10_rgb": "255,184,110",
    "term11_rgb": "0,75,111",
    "term12_rgb": "252,252,255",
    "term13_rgb": "77,103,124",
    "term14_rgb": "139,206,255",
    "term15_rgb": "216,218,223",
    "m3primary_hypr": "rgba(00628eff)",
    "m3onPrimary_hypr": "rgba(ffffffff)",
    "m3primaryContainer_hypr": "rgba(1f7baeff)",
    "m3onPrimaryContainer_hypr": "rgba(fcfcffff)",
    "m3primaryFixed_hypr": "rgba(c9e6ffff)",
    "m3primaryFixedDim_hypr": "rgba(8bceffff)",
    "m3onPrimaryFixed_hypr": "rgba(001e2fff)",
    "m3onPrimaryFixedVariant_hypr": "rgba(004b6fff)",
    "m3secondary_hypr": "rgba(476176ff)",
    "m3onSecondary_hypr": "rgba(ffffffff)",
    "m3secondaryContainer_hypr": "rgba(cae6ffff)",
    "m3onSecondaryContainer_hypr": "rgba(4d677cff)",
    "m3secondaryFixed_hypr": "rgba(cae6ffff)",
    "m3secondaryFixedDim_hypr": "rgba(aecae2ff)",
    "m3onSecondaryFixed_hypr": "rgba(001e2fff)",
    "m3onSecondaryFixedVariant_hypr": "rgba(2f4a5dff)",
    "m3tertiary_hypr": "rgba(864f00ff)",
    "m3onTertiary_hypr": "rgba(ffffffff)",
    "m3tertiaryContainer_hypr": "rgba(a66613ff)",
    "m3onTertiaryContainer_hypr": "rgba(fffbffff)",
    "m3tertiaryFixed_hypr": "rgba(ffdcbdff)",
    "m3tertiaryFixedDim_hypr": "rgba(ffb86eff)",
    "m3onTertiaryFixed_hypr": "rgba(2c1600ff)",
    "m3onTertiaryFixedVariant_hypr": "rgba(693c00ff)",
    "m3error_hypr": "rgba(ba1a1aff)",
    "m3onError_hypr": "rgba(ffffffff)",
    "m3errorContainer_hypr": "rgba(ffdad6ff)",
    "m3onErrorContainer_hypr": "rgba(93000aff)",
    "m3surface_hypr": "rgba(f7f9feff)",
    "m3onSurface_hypr": "rgba(181c1fff)",
    "m3surfaceVariant_hypr": "rgba(dbe3ecff)",
    "m3onSurfaceVariant_hypr": "rgba(40484fff)",
    "m3surfaceDim_hypr": "rgba(d8dadfff)",
    "m3surfaceBright_hypr": "rgba(f7f9feff)",
    "m3surfaceContainerLowest_hypr": "rgba(ffffffff)",
    "m3surfaceContainerLow_hypr": "rgba(f1f4f8ff)",
    "m3surfaceContainer_hypr": "rgba(eceef2ff)",
    "m3surfaceContainerHigh_hypr": "rgba(e6e8edff)",
    "m3surfaceContainerHighest_hypr": "rgba(e0e3e7ff)",
    "m3background_hypr": "rgba(f7f9feff)",
    "m3onBackground_hypr": "rgba(181c1fff)",
    "m3outline_hypr": "rgba(707880ff)",
    "m3outlineVariant_hypr": "rgba(bfc7d0ff)",
    "m3inverseSurface_hypr": "rgba(2d3134ff)",
    "m3inverseOnSurface_hypr": "rgba(eef1f5ff)",
    "m3inversePrimary_hypr": "rgba(8bceffff)",
    "m3shadow_hypr": "rgba(000000ff)",
    "m3scrim_hypr": "rgba(000000ff)",
    "term0_hypr": "rgba(e0e3e7ff)",
    "term1_hypr": "rgba(ba1a1aff)",
    "term2_hypr": "rgba(693c00ff)",
    "term3_hypr": "rgba(2f4a5dff)",
    "term4_hypr": "rgba(00628eff)",
    "term5_hypr": "rgba(476176ff)",
    "term6_hypr": "rgba(707880ff)",
    "term7_hypr": "rgba(40484fff)",
    "term8_hypr": "rgba(864f00ff)",
    "term9_hypr": "rgba(93000aff)",
    "term10_hypr": "rgba(ffb86eff)",
    "term11_hypr": "rgba(004b6fff)",
    "term12_hypr": "rgba(fcfcffff)",
    "term13_hypr": "rgba(4d677cff)",
    "term14_hypr": "rgba(8bceffff)",
    "term15_hypr": "rgba(d8dadfff)"
  }
}